yara.cpython-313-i386-linux-gnu.so
yara_python.libs/libcrypto-4b2ad768.so.1.1
yara_python-4.5.2.dist-info/METADATA
yara_python-4.5.2.dist-info/WHEEL
yara_python-4.5.2.dist-info/top_level.txt
yara_python-4.5.2.dist-info/RECORD
yara_python-4.5.2.dist-info/licenses/LICENSE
