Metadata-Version: 2.4
Name: yara-python
Version: 4.5.2
Summary: Python interface for YARA
Home-page: https://github.com/VirusTotal/yara-python
Author: Victor M. Alvarez
Author-email: plusvic@gmail.com, vmalvarez@virustotal.com
License: Apache 2.0
Classifier: Programming Language :: Python
Classifier: License :: OSI Approved :: Apache Software License
Classifier: Operating System :: OS Independent
Classifier: Development Status :: 5 - Production/Stable
License-File: LICENSE
Dynamic: author
Dynamic: author-email
Dynamic: classifier
Dynamic: description
Dynamic: description-content-type
Dynamic: home-page
Dynamic: license
Dynamic: license-file
Dynamic: summary
